cglearn/CKES_discrete.py
cglearn/CKES_gaussian.py
cglearn/__init__.py
cglearn/ancestralset.py
cglearn/as_freq_tb.py
cglearn/calculate_deviance.py
cglearn/comp_freq_tb.dll
cglearn/comp_freq_tb.so
cglearn/comp_pat.py
cglearn/comp_skel.py
cglearn/compress_freq_table.py
cglearn/cond_ind_test.dll
cglearn/cond_ind_test.so
cglearn/controller_gaussian.py
cglearn/controller_multinom.py
cglearn/draw.py
cglearn/freq_table.py
cglearn/gaussian_skeleton_mkb.py
cglearn/gaussianpclearn.py
cglearn/get_multinom_dist.py
cglearn/get_normal_dist.py
cglearn/get_toy_graph_discrete.py
cglearn/get_toy_graph_gaussian.py
cglearn/graph.py
cglearn/helper.py
cglearn/inducedsubgraph.py
cglearn/is_chain_graph.py
cglearn/isseparated.py
cglearn/istriangulated.py
cglearn/junctiontree.py
cglearn/learn_complex_multinom.py
cglearn/learn_complex_norm.py
cglearn/learn_skeleton_multinom.py
cglearn/learn_skeleton_norm.py
cglearn/mbcsp_discrete.py
cglearn/mbcsp_gaussian.py
cglearn/moralize.py
cglearn/multinom_ci_test.py
cglearn/multinom_pc_learn.py
cglearn/multinom_skeleton_mkb.py
cglearn/norm_ci_test.py
cglearn/pattern.py
cglearn/rmultinom_cg.py
cglearn/rnorm_cg.py
cglearn/skeleton.py
cglearn/toyMulti.csv
cglearn/toygraph.csv
cglearn/triangulate.py
cglearn/ugtojtree.py
cglearn/uig_multinom.py
cglearn/uig_norm.py
cglearn-0.0.1.dist-info/LICENSE
cglearn-0.0.1.dist-info/METADATA
cglearn-0.0.1.dist-info/WHEEL
cglearn-0.0.1.dist-info/top_level.txt
cglearn-0.0.1.dist-info/RECORD
